failmail/__init__.py
failmail/notifier.py
failmail/registry.py
failmail-0.1.1.dist-info/METADATA
failmail-0.1.1.dist-info/WHEEL
failmail-0.1.1.dist-info/licenses/LICENSE
failmail-0.1.1.dist-info/RECORD
