Metadata-Version: 2.4
Name: failmail
Version: 0.1.1
Summary: A Python package to notify users via email when exceptions occur.
Project-URL: Homepage, https://github.com/spyel/failmail
Project-URL: Issues, https://github.com/spyel/failmail/issues
License: MIT License
License-File: LICENSE
Requires-Python: >=3.10
